odoo/addons/dms_field/README.rst
odoo/addons/dms_field/__init__.py
odoo/addons/dms_field/__manifest__.py
odoo/addons/dms_field/data/assets.xml
odoo/addons/dms_field/demo/partner_dms.xml
odoo/addons/dms_field/i18n/dms_field.pot
odoo/addons/dms_field/i18n/es.po
odoo/addons/dms_field/i18n/fr.po
odoo/addons/dms_field/i18n/it.po
odoo/addons/dms_field/i18n/sv.po
odoo/addons/dms_field/models/__init__.py
odoo/addons/dms_field/models/dms_access_group.py
odoo/addons/dms_field/models/dms_directory.py
odoo/addons/dms_field/models/dms_field_mixin.py
odoo/addons/dms_field/models/dms_field_template.py
odoo/addons/dms_field/models/dms_storage.py
odoo/addons/dms_field/models/ir_actions_act_window_view.py
odoo/addons/dms_field/models/ir_ui_view.py
odoo/addons/dms_field/models/res_partner.py
odoo/addons/dms_field/readme/CONFIGURE.md
odoo/addons/dms_field/readme/CONTRIBUTORS.md
odoo/addons/dms_field/readme/DESCRIPTION.md
odoo/addons/dms_field/readme/ROADMAP.md
odoo/addons/dms_field/readme/USAGE.md
odoo/addons/dms_field/security/ir.model.access.csv
odoo/addons/dms_field/security/security.xml
odoo/addons/dms_field/static/description/icon.png
odoo/addons/dms_field/static/description/index.html
odoo/addons/dms_field/static/lib/jsTree/LICENSE
odoo/addons/dms_field/static/lib/jsTree/jstree.js
odoo/addons/dms_field/static/lib/jsTree/themes/default/32px.png
odoo/addons/dms_field/static/lib/jsTree/themes/default/40px.png
odoo/addons/dms_field/static/lib/jsTree/themes/default/style.css
odoo/addons/dms_field/static/lib/jsTree/themes/default/throbber.gif
odoo/addons/dms_field/static/lib/jsTree/themes/proton/30px.png
odoo/addons/dms_field/static/lib/jsTree/themes/proton/32px.png
odoo/addons/dms_field/static/lib/jsTree/themes/proton/LICENSE
odoo/addons/dms_field/static/lib/jsTree/themes/proton/style.css
odoo/addons/dms_field/static/lib/jsTree/themes/proton/throbber.gif
odoo/addons/dms_field/static/lib/jsTree/themes/proton/fonts/titillium/titilliumweb-bold-webfont.eot
odoo_addon_dms_field-18.0.1.1.0.dist-info/METADATA
odoo_addon_dms_field-18.0.1.1.0.dist-info/WHEEL
odoo_addon_dms_field-18.0.1.1.0.dist-info/top_level.txt
odoo_addon_dms_field-18.0.1.1.0.dist-info/RECORD
