Metadata-Version: 2.1
Name: odoo-addon-dms_field
Version: 18.0.1.1.0
Requires-Python: >=3.10
Requires-Dist: odoo-addon-dms==18.0.*
Requires-Dist: odoo==18.0.*
Summary: Create DMS View and allow to use them inside a record
Home-page: https://github.com/OCA/dms
License: LGPL-3
Author: Creu Blanca,Odoo Community Association (OCA)
Author-email: support@odoo-community.org
Classifier: Programming Language :: Python
Classifier: Framework :: Odoo
Classifier: Framework :: Odoo :: 18.0
Classifier: License :: OSI Approved :: GNU Lesser General Public License v3 (LGPLv3)
